{
  "version": 1,
  "tokens": {
    "color.bg": {
      "value": "#f7f1e3",
      "cssVar": "--bg",
      "category": "color"
    },
    "color.panel": {
      "value": "rgba(255, 252, 246, 0.88)",
      "cssVar": "--panel",
      "category": "color"
    },
    "color.panelStrong": {
      "value": "#fffdf8",
      "cssVar": "--panel-strong",
      "category": "color"
    },
    "color.text": {
      "value": "#1b140f",
      "cssVar": "--text",
      "category": "color"
    },
    "color.muted": {
      "value": "#65584c",
      "cssVar": "--muted",
      "category": "color"
    },
    "color.line": {
      "value": "rgba(91, 74, 57, 0.18)",
      "cssVar": "--line",
      "category": "color"
    },
    "color.accent": {
      "value": "#ca5c2d",
      "cssVar": "--accent",
      "category": "color"
    },
    "color.accentStrong": {
      "value": "#9c3f18",
      "cssVar": "--accent-strong",
      "category": "color"
    },
    "color.accentSoft": {
      "value": "#f6d5bf",
      "cssVar": "--accent-soft",
      "category": "color"
    },
    "color.danger": {
      "value": "#a42828",
      "cssVar": "--danger",
      "category": "color"
    },
    "shadow.panel": {
      "value": "0 18px 45px rgba(72, 44, 20, 0.12)",
      "cssVar": "--shadow",
      "category": "shadow"
    },
    "radius.panel": {
      "value": "24px",
      "cssVar": "--radius",
      "category": "radius"
    },
    "font.display": {
      "value": "\"Avenir Next\", \"Hiragino Sans\", sans-serif",
      "cssVar": "--font-display",
      "category": "font"
    },
    "font.body": {
      "value": "\"Hiragino Sans\", \"Noto Sans JP\", sans-serif",
      "cssVar": "--font-body",
      "category": "font"
    }
  }
}
